{
    "title": "Get in Touch",
    "subtitle": "Let’s create something beautiful together. Reach out to discuss your wedding film.",
    "contactInfo": {
        "email": "hello@vivahbts.com",
        "phone": "+91 98765 43210",
        "location": "Mumbai, India",
        "instagram": "@vivah_bts"
    },
    "formLabels": {
        "name": "Your Name",
        "email": "Email Address",
        "date": "Wedding Date",
        "location": "Venue Location",
        "message": "Tell us about your story...",
        "submit": "Send Message"
    }
}